[
  {
    "id": "monuments",
    "title": "Monuments",
    "osmium_filter": "nrw/historic=monument",
    "osmWiki": "Tag:historic%3Dmonument",
    "requiredTags": ["name", "start_date", "height", "wikidata"]
  },
  {
    "id": "memorials",
    "title": "Memorials",
    "osmium_filter": "nrw/historic=memorial",
    "requiredTags": ["name", "start_date", "height", "wikidata"]
  },
  {
    "id": "heritage",
    "title": "Site/building/object registered by an official heritage organisation",
    "osmium_filter": "nrw/heritage",
    "requiredTags": ["name"]
  }
]
